{
  "uuid": "8abdc028-d068-4b8a-b976-bd57506ebafc",
  "title": "China Preparing For War, Xi Jinping Says",
  "description": "",
  "keywords": "",
  "snippet": "On Tuesday, Chinese Communist President Xi Jinping declared his country will focus on preparing for war.\n\n\u201cChina is preparing for war, its President Xi Jinpin...",
  "url": "https://www.dailywire.com/news/china-preparing-for-war-xi-jinping-says",
  "image_url": "https://dw-wp-production.imgix.net/2022/11/GettyImages-1244185347.jpg?w=1200&h=800&ixlib=react-9.3.0",
  "language": "en",
  "published_at": "2022-11-08T15:49:28.000000Z",
  "source": "dailywire.com",
  "categories": [
    "politics",
    "general"
  ],
  "relevance_score": 38.9722
}