{
  "uuid": "e2992383-b0b7-4db2-a8e1-adc74d7bdae4",
  "title": "China hopes EU will abandon trade, economic restrictions \u2014 Xi Jinping",
  "description": "The Chinese leader received European Commission President Ursula von der Leyen and European Council President Antonio Costa at the Great Hall of the People in B...",
  "keywords": "",
  "snippet": "BEIJING, July 24. /TASS/. China\u2019s authorities hope that the leadership of the European Union will abandon its restrictions policy in the trade and economic ar...",
  "url": "https://tass.com/world/1993757",
  "image_url": "https://tass.com/img/blocks/common/tass_logo_share_eng.png",
  "language": "en",
  "published_at": "2025-07-24T12:13:53.000000Z",
  "source": "tass.com",
  "categories": [
    "general"
  ],
  "relevance_score": 37.174
}