{
  "uuid": "aab04782-6c33-4a20-a3bd-24ef6805ad7f",
  "title": "Trump May Meet Xi Jinping During South Korea Trip",
  "description": "President Trump is planning to potentially meet with Chinese President XI JINPING during a trip to South Korea\u00a0next\u00a0month.",
  "keywords": "",
  "snippet": "President Trump is planning to potentially meet with Chinese President XI JINPING during a trip to South Korea next month.",
  "url": "https://www.theyeshivaworld.com/news/liveblogs/live-blog/2446329/trump-may-meet-xi-jinping-during-south-korea-trip.html",
  "image_url": "https://yeshivaworld.b-cdn.net/wp-content/uploads/2025/09/WhatsApp-Image-2025-09-06-at-20.39.16_68b62666.jpg",
  "language": "en",
  "published_at": "2025-09-07T00:46:28.000000Z",
  "source": "theyeshivaworld.com",
  "categories": [
    "general"
  ],
  "relevance_score": 37.706833
}