{
  "uuid": "69387163-ba00-480b-b7d8-b31b8ad4531a",
  "title": "Biden will meet with China's Xi Jinping next month, White House says",
  "description": "President Joe Biden will meet with Chinese President Xi Jinping next month, the White House says.",
  "keywords": "Defense, Breaking News: Politics, Politics, U.S. Economy, Joe Biden, Government and politics, business news",
  "snippet": "China's President Xi Jinping and U.S. President Joe Biden at the G20 Summit in Nusa Dua on the Indonesian island of Bali on Nov. 14, 2022.\n\nWASHINGTON \u2014 Presi...",
  "url": "https://www.cnbc.com/2023/10/31/biden-will-meet-with-chinas-xi-jinping-next-month-white-house-says.html",
  "image_url": "https://image.cnbcfm.com/api/v1/image/107324859-1698458820884-gettyimages-1244770277-AFP_32NG9M9.jpeg?v=1698777744&w=1920&h=1080",
  "language": "en",
  "published_at": "2023-10-31T18:50:05.000000Z",
  "source": "cnbc.com",
  "categories": [
    "general",
    "business"
  ],
  "relevance_score": 37.61373
}