{
  "uuid": "a3bec0e6-37df-41c9-860e-a516b1f8b13e",
  "title": "Xi Jinping Fears Chinese Communist Party May Collapse: Report",
  "description": "Chinese President Xi Jinping for the past some time has been issuing warnings regarding the collapse of the Communist Party of China (CCP) amidst 415 million ac...",
  "keywords": "Chinese Communist Party, Xi Jinping, China Xi Jinping",
  "snippet": "CCP has fear that it might suffer the same fate as the Soviet Union.\n\nChinese President Xi Jinping for the past some time has been issuing warnings regarding th...",
  "url": "https://www.ndtv.com/world-news/xi-jinping-fears-chinese-communist-party-may-collapse-report-4220828",
  "image_url": "https://c.ndtvimg.com/2021-10/jmc9vm9o_china-xi-jinping-new-reuters_625x300_25_October_21.jpg",
  "language": "en",
  "published_at": "2023-07-19T04:51:36.000000Z",
  "source": "ndtv.com",
  "categories": [
    "general"
  ],
  "relevance_score": 39.034454
}